README.md
setup.py
django_fflag.egg-info/PKG-INFO
django_fflag.egg-info/SOURCES.txt
django_fflag.egg-info/dependency_links.txt
django_fflag.egg-info/requires.txt
django_fflag.egg-info/top_level.txt
fflag/__init__.py
fflag/apps.py
fflag/default_settings.py
fflag/middleware.py
fflag/models.py
fflag/management/__init__.py
fflag/management/pprint.py
fflag/management/commands/__init__.py
fflag/management/commands/fflag_add_part_ids.py
fflag/management/commands/fflag_get.py
fflag/management/commands/fflag_list.py
fflag/management/commands/fflag_list_enabled_for.py
fflag/management/commands/fflag_set_part.py
fflag/management/commands/fflag_set_part_ids.py