Metadata-Version: 2.1
Name: django-fflag
Version: 0.2.0
Summary: Lightweight feature flags for django
Home-page: https://github.com/mixkorshun/django-fflag
Author: Vladislav Bakin
Author-email: vladislav@bakin.me
Maintainer: Vladislav Bakin
Maintainer-email: vladislav@bakin.me
License: MIT
Keywords: feature-flags,django
Platform: UNKNOWN
Classifier: Development Status :: 5 - Production/Stable
Classifier: Intended Audience :: Developers
Classifier: Environment :: Web Environment
Classifier: Framework :: Django
Classifier: Natural Language :: English
Classifier: License :: OSI Approved :: MIT License
Classifier: Programming Language :: Python
Classifier: Programming Language :: Python :: 3
Classifier: Programming Language :: Python :: 3.6
Classifier: Programming Language :: Python :: 3.7
Classifier: Programming Language :: Python :: 3.8
